sample_package_tst/__init__.py
sample_package_tst-0.0.1.dist-info/LICENSE.txt
sample_package_tst-0.0.1.dist-info/METADATA
sample_package_tst-0.0.1.dist-info/WHEEL
sample_package_tst-0.0.1.dist-info/top_level.txt
sample_package_tst-0.0.1.dist-info/RECORD
