Metadata-Version: 2.1
Name: sample_package_tst
Version: 0.0.1
Summary: First package
Author: DefAir
Author-email: deforkind@gmail.com
Classifier: Programming Language :: Python :: 3.8
Classifier: License :: OSI Approved :: MIT License
Classifier: Operating System :: OS Independent
Requires-Python: >=3.6
License-File: LICENSE.txt
